totus/__init__.py
totus/errors.py
totus/reference.py
totus/totus.py
totus/validate.py
totus/dto/POI.py
totus/dto/ValidatedEmail.py
totus-0.1.4.dist-info/METADATA
totus-0.1.4.dist-info/WHEEL
totus-0.1.4.dist-info/licenses/LICENSE.md
totus-0.1.4.dist-info/RECORD
