Metadata-Version: 2.4
Name: totus
Version: 0.1.4
Summary: Client API for GoTotus; your universal development toolkit
Project-URL: Homepage, https://github.com/GoTotus/pytotus
Project-URL: Documentation, https://docs.gototus.com/
Author-email: GoTotus Team <support@gototus.com>
License-Expression: BSD-3-Clause
License-File: LICENSE.md
Requires-Python: >=3.6
Requires-Dist: requests>=2.28.0
